psup/__init__.py
psup/__main__.py
psup/onlinestory.py
psup/story.py
psup/storyerror.py
psup-0.1.2.3a0.dist-info/LICENSE
psup-0.1.2.3a0.dist-info/METADATA
psup-0.1.2.3a0.dist-info/WHEEL
psup-0.1.2.3a0.dist-info/entry_points.txt
psup-0.1.2.3a0.dist-info/top_level.txt
psup-0.1.2.3a0.dist-info/RECORD
