Metadata-Version: 2.1
Name: psup
Version: 0.1.2.3a0
Summary: A simple library for making complex stories and games.
Home-page: https://github.com/EnokiUN/psup
Author: EnokiUN
License: MIT
Download-URL: https://github.com/EnokiUN/psup/archive/refs/tags/Release-0-1-1-5a.tar.gz
Project-URL: Documentation, https://psup.readthedocs.io/en/latest/
Project-URL: Issue tracker, https://github.com/enokiun/psup/issues
Platform: UNKNOWN
Classifier: Development Status :: 5 - Production/Stable
Classifier: License :: OSI Approved :: MIT License
Classifier: Intended Audience :: Developers
Classifier: Natural Language :: English
Classifier: Operating System :: OS Independent
Classifier: Programming Language :: Python :: 3.8
Classifier: Programming Language :: Python :: 3.9
Classifier: Topic :: Internet
Classifier: Topic :: Software Development :: Libraries
Classifier: Topic :: Utilities
Requires-Python: >=3.8.0
License-File: LICENSE
